flask_dxcaptcha/__init__.py
flask_dxcaptcha/captchaclient.py
flask_dxcaptcha/captcharesponse.py
flask_dxcaptcha/ctuclient.py
flask_dxcaptcha/cturequest.py
flask_dxcaptcha/cturesponse.py
flask_dxcaptcha/cturesponsestatus.py
flask_dxcaptcha/cturesult.py
flask_dxcaptcha/hitrule.py
flask_dxcaptcha/risklevel.py
flask_dxcaptcha/risktype.py
flask_dxcaptcha/suggestion.py
flask_dxcaptcha/suggestpolicy.py
Flask_DXCaptcha-1.0.8.dist-info/LICENSE
Flask_DXCaptcha-1.0.8.dist-info/METADATA
Flask_DXCaptcha-1.0.8.dist-info/WHEEL
Flask_DXCaptcha-1.0.8.dist-info/top_level.txt
Flask_DXCaptcha-1.0.8.dist-info/RECORD
