Metadata-Version: 2.1
Name: Flask-DXCaptcha
Version: 1.0.8
Summary: Flask-DXCaptcha是依赖顶象科技提供的无感验证功能开发的Flask 扩展
Home-page: https://github.com/durban89/flask_dxcaptcha
Author: durban zhang
Author-email: durban.zhang@gmail.com
License: MIT
Platform: any
Classifier: Environment :: Web Environment
Classifier: Framework :: Flask
Classifier: Intended Audience :: Developers
Classifier: License :: OSI Approved :: MIT License
Classifier: Operating System :: OS Independent
Classifier: Programming Language :: Python :: 3
Classifier: Topic :: Internet :: WWW/HTTP :: Dynamic Content
Classifier: Topic :: Software Development :: Libraries :: Python Modules
Requires-Python: >=3.7.4
Requires-Dist: Flask (>=1.1.1)
